warskald/__init__.py
warskald/_globals.py
warskald/attr_dict.py
warskald/git_util.py
warskald/ng_scaffold.py
warskald/ng_serve.py
warskald/ngwidget.py
warskald/profiler.py
warskald/pybuild.py
warskald/req_utils.py
warskald/reqs_gen.py
warskald/run_ngwidget.py
warskald/s3cli.py
warskald/utils.py
warskald/ws_config.py
warskald/ws_latest.py
warskald/wspub.py
warskald-0.0.55.dist-info/LICENSE
warskald-0.0.55.dist-info/METADATA
warskald-0.0.55.dist-info/WHEEL
warskald-0.0.55.dist-info/entry_points.txt
warskald-0.0.55.dist-info/top_level.txt
warskald-0.0.55.dist-info/RECORD
