Metadata-Version: 2.1
Name: warskald
Version: 0.0.55
Summary: Common utilities for the workspace
Author: Joseph Bochinski
License-File: LICENSE
Requires-Dist: flask
Requires-Dist: case-converter
Requires-Dist: pyyaml
Requires-Dist: toml
